keplertools-1.4.1.dist-info/RECORD
keplertools-1.4.1.dist-info/WHEEL
keplertools-1.4.1.dist-info/top_level.txt
keplertools-1.4.1.dist-info/METADATA
keplertools-1.4.1.dist-info/licenses/LICENSE
keplertools/CyRV.cpython-312-darwin.so
keplertools/keplerSTM.py
keplertools/CyKeplerSTM.cpython-312-darwin.so
keplertools/fun.py
keplertools/Cyeccanom.cpython-312-darwin.so
keplertools/__init__.py
keplertools/RV_C/__init__.py
keplertools/KeplerSTM_C/__init__.py
keplertools/eccanom_C/__init__.py
