Metadata-Version: 2.1
Name: keplertools
Version: 1.4.1
Summary: Two-body orbital propagation tools
Home-page: https://github.com/dsavransky/keplertools
Author: Dmitry Savransky
Author-email: ds264@cornell.edu
Classifier: Programming Language :: Python :: 3.10
Classifier: Programming Language :: Python :: 3.11
Classifier: Programming Language :: Python :: 3.12
Classifier: Programming Language :: Python :: 3.13
Classifier: License :: OSI Approved :: BSD License
Classifier: Operating System :: OS Independent
License-File: LICENSE
